ionbus_utils/__init__.py
ionbus_utils/_version.py
ionbus_utils/base_utils.py
ionbus_utils/cache_utils.md
ionbus_utils/cache_utils.py
ionbus_utils/date_utils.py
ionbus_utils/enumerate.py
ionbus_utils/exceptions.py
ionbus_utils/file_utils.md
ionbus_utils/file_utils.py
ionbus_utils/general.py
ionbus_utils/general_classes.py
ionbus_utils/group_utils.py
ionbus_utils/logging.md
ionbus_utils/logging_utils.py
ionbus_utils/pandas_utils.md
ionbus_utils/pandas_utils.py
ionbus_utils/readme.md
ionbus_utils/readme_pip.md
ionbus_utils/regex_utils.py
ionbus_utils/subprocess_utils.md
ionbus_utils/subprocess_utils.py
ionbus_utils/time_utils.md
ionbus_utils/time_utils.py
ionbus_utils/crypto_utils/__init__.py
ionbus_utils/crypto_utils/auth_utils.py
ionbus_utils/crypto_utils/crypto_utils.py
ionbus_utils/crypto_utils/readme.md
ionbus_utils/git_utils/__init__.py
ionbus_utils/git_utils/__main__.py
ionbus_utils/git_utils/auto_tag.py
ionbus_utils/git_utils/base_git.py
ionbus_utils/git_utils/deploy.py
ionbus_utils/git_utils/readme.md
ionbus_utils/tests/__init__.py
ionbus_utils/tests/conftest.py
ionbus_utils/tests/test_base_utils.py
ionbus_utils/tests/test_cache_utils.py
ionbus_utils/tests/test_crypto_utils.py
ionbus_utils/tests/test_date_utils.py
ionbus_utils/tests/test_enumerate.py
ionbus_utils/tests/test_exceptions.py
ionbus_utils/tests/test_file_utils.py
ionbus_utils/tests/test_general.py
ionbus_utils/tests/test_general_classes.py
ionbus_utils/tests/test_git_utils.py
ionbus_utils/tests/test_group_utils.py
ionbus_utils/tests/test_logging_utils.py
ionbus_utils/tests/test_pandas_utils.py
ionbus_utils/tests/test_regex_utils.py
ionbus_utils/tests/test_subprocess_utils.py
ionbus_utils/tests/test_time_utils.py
ionbus_utils/tests/test_yaml_utils.py
ionbus_utils/yaml_utils/__init__.py
ionbus_utils/yaml_utils/pdyaml.py
ionbus_utils/yaml_utils/readme.md
ionbus_utils-1.0.2.1.dist-info/METADATA
ionbus_utils-1.0.2.1.dist-info/WHEEL
ionbus_utils-1.0.2.1.dist-info/top_level.txt
ionbus_utils-1.0.2.1.dist-info/RECORD
