Metadata-Version: 2.1
Name: ionbus-utils
Version: 1.0.2.1
Summary: Package of useful python utilities
Author-email: Charles Lewis <dev@ionbus.info>
Classifier: Programming Language :: Python :: 3
Classifier: License :: OSI Approved :: MIT License
Classifier: Operating System :: OS Independent
Requires-Python: >=3.9
Requires-Dist: cryptography>=44.0
Requires-Dist: duckdb>=0.10
Requires-Dist: packaging>=23.1
Requires-Dist: pandas<3.0.0
Requires-Dist: polars
Requires-Dist: pyarrow>=16.0.1
Requires-Dist: pydantic>=2.7.2
Requires-Dist: pytest
Requires-Dist: PyYAML>=6.0.1
Requires-Dist: requests~=2.31
Requires-Dist: setuptools
Requires-Dist: typing-extensions>=4.7.1
Requires-Dist: eval-type-backport; python_version < "3.10"
Requires-Dist: backports.strenum>=0.4.1; python_version < "3.11"
